{
  "FFlagOptimizeMouseLockState": true,
  "DFStringSchedulerRemoveWorkers": "Auto",
  "DFStringRenderFramerateManagerMode": "Automatic",
  "DFIntRenderFramerateManagerTargetFps": 240,
  "DFStringPhysicsSolver": "RK4",
  "DFIntPhysicsSolverMaxCSteps": 3,
  "DFIntPhysicsSolverMaxDSteps": 2,
  "DFIntPhysicsSolverMaxPSteps": 4,
  "DFIntPhysicsSolverMaxVSteps": 1,
  "DFIntPhysicsSolverMinCSteps": 1,
  "DFIntPhysicsSolverMinDSteps": 1,
  "DFIntPhysicsSolverMinPSteps": 1,
  "DFIntPhysicsSolverMinVSteps": 1,
  "DFIntPhysicsSolverMaxSubSteps": 6,
  "DFIntPhysicsSolverMaxResets": 3,
  "DFIntPhysicsSolverMaxTime": 0.0167,
  "FFlagOptimizePhysicsStepper": true,
  "FFlagOptimizePhysicsSolver": true,
  "FFlagOptimizePhysicsSweep": true,
  "FFlagOptimizePhysicsConstraints": true,
  "DFIntPhysicsConstraintsMax": 256,
  "DFIntPhysicsSweepResolution": 0.1,
  "DFIntPhysicsSweepMaxHits": 8,
  "DFIntPhysicsSweepMaxDistance": 200,
  "DFIntPhysicsSweepMinSpeed": 500,
  "FFlagOptimizeParticles": true,
  "DFIntParticlesMaxCount": 512,
  "DFIntParticlesMaxLifetime": 10,
  "DFIntParticlesMaxSpeed": 100,
  "DFIntParticlesMinSpeed": 50,
  "FFlagOptimizeShadows": true,
  "DFIntShadowResolution": 512,
  "DFIntShadowMaxDistance": 100,
  "FFlagOptimizePostProcessing": true,
  "DFIntPostProcessingQuality": 1,
  "DFIntPostProcessingBloomThreshold": 0.5,
  "DFIntPostProcessingBloomIntensity": 0.2,
  "DFIntPostProcessingColorGrading": 1,
  "DFIntPostProcessingDepthOfField": 0,
  "FFlagOptimizeAudio": true,
  "DFIntAudioQuality": 1,
  "DFIntAudioMaxChannels": 32,
  "DFIntAudioMaxDistance": 100,
  "DFIntAudioMinDistance": 10,
  "FFlagOptimizeAnimations": true,
  "DFIntAnimationQuality": 1,
  "DFIntAnimationMaxParticles": 64,
  "DFIntAnimationMaxBones": 128,
  "DFIntAnimationMaxKeyframes": 512,
  "DFIntAnimationMaxTracks": 16,
  "FFlagOptimizeNetwork": true,
  "DFIntNetworkUpdateRate": 60,
  "DFIntNetworkMaxUpdatesPerSecond": 30,
  "DFIntNetworkMaxPhysicsRate": 60,
  "DFIntNetworkMaxPartRate": 60,
  "DFIntNetworkMaxJointRate": 60,
  "DFIntNetworkMaxRaycastRate": 60,
  "DFIntNetworkMaxTerrainRate": 60,
  "FFlagOptimizeInput": true,
  "DFIntInputBufferSize": 10,
  "DFIntInputMaxCommandsPerSecond": 60,
  "FFlagOptimizeRendering": true,
  "DFIntRenderingMaxCpuFrames": 2,
  "DFIntRenderingMaxGpuFrames": 2,
  "FFlagOptimizeLighting": true,
  "DFIntLightingQuality": 1,
  "DFIntLightingMaxLights": 4,
  "DFIntLightingMaxShadows": 2,
  "DFIntLightingMaxBounces": 1,
  "DFIntLightingMaxResolution": 256,
  "DFIntLightingMaxDistance": 50,
  "FFlagOptimizeAmbientOcclusion": true,
  "DFIntAmbientOcclusionQuality": 1,
  "DFIntAmbientOcclusionRadius": 1,
  "DFIntAmbientOcclusionIntensity": 0.5,
  "DFIntAmbientOcclusionMaxDistance": 10,

  "TextureQuality": 1,
  "HardwareMouse": true,
  "VRR": false,
  "Fullscreen": true,
  "ShowPerfStats": false,
  "ShowDevelopmentGui": false,
  "FFlagGlobalWindRendering": true,
  "FFlagGlobalWindActivated": true,
  "DFIntFRMMinGrassDistance": 0.5,
  "DFIntFRMMaxGrassDistance": 12.5,
  "GraphicsQualityLevel": 1,
  "FFlagQuickSynchronousYield": true,
  "FFlagDynamicYieldPoints": true,
  "FFlagLightYieldNew": true,
  "FFlagEnableTextureStreamingV2": true,
  "FFlagRenderGpuTextureCompressor": true,
  "FFlagGraphicsCheckComputeSupport": true,
  "FFlagGraphicsTextureCopy": true,
  "FFlagGraphicsDeviceEvents": true,
  "FFlagGraphicsEnableD3D10Compute": true,
  "FFlagFastSpawnDeserialization": true,
  "FFlagFastGPULightCulling3": true,
  "FFlagGpuGeometryManager7": true,
  "FFlagCommitToGraphicsQualityFix": true,
  "FFlagFixGraphicsQuality": true,
  "FFlagEnableAnimationsV3": true,

  "DFIntRayPickBatchSize": 512,
  "DFIntPreloadBatchSize": 128,
  "DFIntHttpCurlConnectionCacheSize": 87108864,
  "FIntEmotesAnimationsPerPlayerCacheSize": 67108864,
  "DFIntUserIdPlayerNameCacheSize": 8388608,
  "DFIntUserIdPlayerNameLifetimeSeconds": 21600,
  "DFIntCSGLevelOfDetailSwitchingDistance": 10,
  "DFIntCSGLevelOfDetailSwitchingDistanceL12": 25,
  "DFIntCSGLevelOfDetailSwitchingDistanceL23": 50,
  "DFIntCSGLevelOfDetailSwitchingDistanceL34": 75,
  "FIntFRMMinGrassDistance": 10,
  "FIntFRMMaxGrassDistance": 50,
  "FIntRenderGrassDetailStrands": 25,
  "FIntRenderGrassHeightScaler": 1.5,
  "FIntRenderShadowIntensity": 0.5,
  "FLogNetwork": 7,
  "DFIntTaskSchedulerTargetFps": "9999",
  "FFlagEnableQuickGameLaunch": true,

  "FFlagUseOptimisticCacheLocks": true,
  "DFStringCacheLockMode": "Optimistic",
  "FFlagSynchronousYield": false,
  "FFlagYieldAfterMaxTime": false,
  "DFIntYieldBreakpoints": 5000,
  "FFlagUseOptimizedMouseLockState": true,
  "DFFlagUseNewPhysicsStepper": true,
  "DFIntPhysicsStepperFramerate": 120,
  "DFFlagPhysicsStepperSendRate": true,
  "DFFlagPhysicsStepperMaxSteps": true,
  "DFFlagPhysicsStepperElasticity": true,
  "DFFlagDisableBrowserCore": true,
  "DFFlagForceNetworkAsync": true,


  "FFlagEnableNewAudio": true,
  "FFlagEnableNewAudioLoading": true,
  "FFlagUseNewLocalizationSetup": true,


  "FFlagEnableLuaSignal": true,
  "DFFlagEnableDependentLuaSignal": true,
  "DFFlagEnableLuaSignalGC": true,
  "DFFlagTextureQualityOverrideEnabled": true,
  "DFIntTextureQualityOverride": 0,
  "FFlagEnableLuaEventAnnotations": true,
  "FFlagEnableLuaSignalAnnotations": true,
  "FFlagEnableLuaTableAnnotations": true,
  "FFlagEnableLuaTupleAnnotations": true,
  "FFlagEnableLuauTypeChecking": true,
  "FFlagEnableLuauJit": true,
  "FFlagEnableLuauLocalRendering": true,
  "FFlagEnableLuauModuleRendering": true,
  "FFlagEnableLuauDiagnostics": true,
  "FFlagEnableLuauMinify": true,
  "FFlagEnableLuauObfuscation": true,
  "DFStringLuauDiagnosticsStringCategory": "Function",
  "DFStringLuauDiagnosticsStringVerbosity": "Verbose",
  "FFlagEnableProfilerFrontend": true,
  "FFlagEnableProfilerFlamegraph": true,
  "DFStringProfilerFlamegraphColumnSort": "ExclusiveTime",
  "FFlagEnableProfilerMoreInfoInSummary": true
}
